WPNames/__init__.py
WPNames/app.py
WPNames-1.0.0.dist-info/METADATA
WPNames-1.0.0.dist-info/WHEEL
WPNames-1.0.0.dist-info/top_level.txt
WPNames-1.0.0.dist-info/RECORD
