Metadata-Version: 2.1
Name: WPNames
Version: 1.0.0
Summary: WordPress Usernames Scanner
Author: CyberTitus
Author-email: <cybertitus@proton.me>
Keywords: python,WordPress,WPScan,WP,WordPress-Usernames,Usernames,Cyber-Security
Classifier: Development Status :: 1 - Planning
Classifier: Intended Audience :: Developers
Classifier: Programming Language :: Python :: 3
Classifier: Operating System :: Unix
Classifier: Operating System :: MacOS :: MacOS X
Classifier: Operating System :: Microsoft :: Windows
Requires-Dist: requests
